<?xml version="1.0" encoding="UTF-8" ?>
<!DOCTYPE mapper PUBLIC "-//mybatis.org//DTD Mapper 3.0//EN"
        "http://mybatis.org/dtd/mybatis-3-mapper.dtd">
<mapper namespace="tw.edu.ncu.osa.venue_reservation_service.mapper.BookingMapper">

    <!-- ========================================== -->
    <!-- 結果映射 -->
    <!-- ========================================== -->

    <resultMap id="bookingVOResultMap" type="tw.edu.ncu.osa.venue_reservation_service.model.vo.BookingVO">
        <result column="id" property="id"/>
        <result column="venue_name" property="venueName"/>
        <result column="booking_date" property="bookingDate"/>
        <result column="slots" property="slots" typeHandler="tw.edu.ncu.osa.venue_reservation_service.util.TimeSlotTypeHandler"/>
        <result column="status" property="status"/>
        <result column="created_at" property="createdAt"/>
        <result column="purpose" property="purpose"/>
        <result column="p_count" property="pCount"/>
        <result column="contact_info" property="contactInfo"/>
        <result column="equipments" property="equipments" typeHandler="tw.edu.ncu.osa.venue_reservation_service.util.CommaSeparatedListTypeHandler"/>
    </resultMap>

    <!-- ========================================== -->
    <!-- 衝突檢查 -->
    <!-- ========================================== -->

    <select id="countConflictingApprovedBookings" resultType="int">
        SELECT COUNT(*) FROM bookings
        WHERE venue_id = #{venueId}
        AND booking_date = #{date}
        AND status = 2
        AND (time_slots &amp; #{mask}) != 0
    </select>

    <!-- ========================================== -->
    <!-- 基本 CRUD 操作 -->
    <!-- ========================================== -->

    <insert id="insertBooking" useGeneratedKeys="true" keyProperty="id">
        INSERT INTO bookings (venue_id, user_id, booking_date, time_slots, status, purpose, p_count, contact_info, version)
        VALUES (#{venueId}, #{userId}, #{bookingDate}, #{timeSlots}, #{status}, #{purpose}, #{pCount}, #{contactInfo}, 1)
    </insert>

    <select id="selectById" resultType="tw.edu.ncu.osa.venue_reservation_service.model.entity.Booking">
        SELECT id, venue_id, user_id, booking_date, time_slots, status, purpose, p_count, contact_info, version, created_at, updated_at
        FROM bookings
        WHERE id = #{id}
    </select>

    <select id="selectByUserId" resultType="tw.edu.ncu.osa.venue_reservation_service.model.entity.Booking">
        SELECT id, venue_id, user_id, booking_date, time_slots, status, purpose, p_count, contact_info, version, created_at, updated_at
        FROM bookings
        WHERE user_id = #{userId}
        ORDER BY created_at DESC
    </select>

    <!-- ========================================== -->
    <!-- 更新操作 -->
    <!-- ========================================== -->

    <update id="updateStatusWithVersion">
        UPDATE bookings
        SET status = #{newStatus},
            version = version + 1
        WHERE id = #{id} AND version = #{oldVersion}
    </update>

    <update id="updateBooking">
        UPDATE bookings
        SET venue_id = #{venueId},
            booking_date = #{bookingDate},
            time_slots = #{timeSlots},
            status = #{status},
            purpose = #{purpose},
            p_count = #{pCount},
            contact_info = #{contactInfo},
            version = version + 1
        WHERE id = #{id}
    </update>

    <delete id="deleteBookingEquipmentByBookingId">
        DELETE FROM booking_equipment WHERE booking_id = #{bookingId}
    </delete>

    <!-- ========================================== -->
    <!-- 關聯操作 -->
    <!-- ========================================== -->

    <insert id="insertBookingEquipment">
        INSERT INTO booking_equipment (booking_id, equipment_id)
        VALUES (#{bookingId}, #{equipmentId})
    </insert>

    <!-- ========================================== -->
    <!-- 日曆視圖查詢 -->
    <!-- ========================================== -->

    <select id="selectApprovedBookingsByDateRange" resultType="tw.edu.ncu.osa.venue_reservation_service.model.entity.Booking">
        SELECT id, venue_id, user_id, booking_date, time_slots, status, purpose, p_count, contact_info, version, created_at, updated_at
        FROM bookings
        WHERE venue_id = #{venueId}
          AND booking_date BETWEEN #{startDate} AND #{endDate}
          AND status = 2
        ORDER BY booking_date ASC
    </select>

    <select id="selectUserBookingsByDateRange" resultType="tw.edu.ncu.osa.venue_reservation_service.model.entity.Booking">
        SELECT id, venue_id, user_id, booking_date, time_slots, status, purpose, p_count, contact_info, version, created_at, updated_at
        FROM bookings
        WHERE venue_id = #{venueId}
          AND user_id = #{userId}
          AND booking_date BETWEEN #{startDate} AND #{endDate}
        ORDER BY booking_date ASC
    </select>

    <select id="selectBookingsByDateRangeForCalendar" resultMap="bookingVOResultMap">
        SELECT
            b.id,
            v.name AS venue_name,
            b.booking_date,
            b.time_slots AS slots,
            b.status,
            b.created_at,
            b.purpose,
            b.p_count,
            b.contact_info,
            GROUP_CONCAT(DISTINCT e.name SEPARATOR ',') AS equipments
        FROM bookings b
        INNER JOIN venues v ON b.venue_id = v.id
        LEFT JOIN booking_equipment be ON b.id = be.booking_id
        LEFT JOIN equipments e ON be.equipment_id = e.id
        WHERE b.venue_id = #{venueId}
          AND b.booking_date BETWEEN #{startDate} AND #{endDate}
        GROUP BY b.id, v.name, b.booking_date, b.time_slots, b.status, b.created_at, b.purpose, b.p_count, b.contact_info
        ORDER BY b.booking_date ASC, b.created_at ASC
    </select>

    <!-- ========================================== -->
    <!-- 查詢衝突的「審核中」預約 -->
    <!-- ========================================== -->

    <select id="selectPendingConflictingBookings" resultType="tw.edu.ncu.osa.venue_reservation_service.model.entity.Booking">
        SELECT id, venue_id, user_id, booking_date, time_slots, status, purpose, p_count, contact_info, version, created_at, updated_at
        FROM bookings
        WHERE venue_id = #{venueId}
        AND booking_date = #{date}
        AND status = 1
        AND (time_slots &amp; #{mask}) != 0
        AND id != #{excludeBookingId}
    </select>

    <!-- ==========================================
         高級查詢：多維度篩選和分頁
         ========================================== -->

    <!-- 多維度篩選查詢：支援場地、狀態、日期範圍篩選 + 分頁 -->
    <select id="queryMyBookingsWithFilters" resultMap="bookingVOResultMap">
        SELECT
            b.id,
            v.name AS venue_name,
            b.booking_date,
            b.time_slots AS slots,
            b.status,
            b.created_at,
            b.purpose,
            b.p_count,
            b.contact_info,
            GROUP_CONCAT(DISTINCT e.name SEPARATOR ',') AS equipments
        FROM bookings b
        INNER JOIN venues v ON b.venue_id = v.id
        LEFT JOIN booking_equipment be ON b.id = be.booking_id
        LEFT JOIN equipments e ON be.equipment_id = e.id
        WHERE b.user_id = #{userId}
        <if test="venueId != null">
            AND b.venue_id = #{venueId}
        </if>
        <if test="statusList != null and statusList.size() > 0">
            AND b.status IN
            <foreach item="status" collection="statusList" open="(" separator="," close=")">
                #{status}
            </foreach>
        </if>
        <if test="startDate != null">
            AND b.booking_date &gt;= #{startDate}
        </if>
        <if test="endDate != null">
            AND b.booking_date &lt;= #{endDate}
        </if>
        GROUP BY b.id, v.name, b.booking_date, b.time_slots, b.status, b.created_at, b.purpose, b.p_count, b.contact_info
        ORDER BY b.created_at DESC
        LIMIT #{limit} OFFSET #{offset}
    </select>

    <!-- 計算符合篩選條件的預約總數 -->
    <select id="countMyBookingsWithFilters" resultType="long">
        SELECT COUNT(DISTINCT b.id)
        FROM bookings b
        WHERE b.user_id = #{userId}
        <if test="venueId != null">
            AND b.venue_id = #{venueId}
        </if>
        <if test="statusList != null and statusList.size() > 0">
            AND b.status IN
            <foreach item="status" collection="statusList" open="(" separator="," close=")">
                #{status}
            </foreach>
        </if>
        <if test="startDate != null">
            AND b.booking_date &gt;= #{startDate}
        </if>
        <if test="endDate != null">
            AND b.booking_date &lt;= #{endDate}
        </if>
    </select>

</mapper>

